ironcore_alloy/__init__.py
ironcore_alloy/ironcore_alloy.py
ironcore_alloy/libironcore_alloy.so
ironcore_alloy-0.13.1.dist-info/METADATA
ironcore_alloy-0.13.1.dist-info/WHEEL
ironcore_alloy-0.13.1.dist-info/licenses/LICENSE.txt
ironcore_alloy-0.13.1.dist-info/RECORD
