Metadata-Version: 2.4
Name: ironcore-alloy
Version: 0.13.1
Summary: Python bindings to the IronCore Labs Alloy SDK. Used for encrypting and decrypting embeddings and their related metadata.
Project-URL: Homepage, https://ironcorelabs.com
Author-email: IronCore Labs <info@ironcorelabs.com>
License-File: LICENSE.txt
Classifier: License :: OSI Approved :: GNU Affero General Public License v3 or later (AGPLv3+)
Classifier: Operating System :: MacOS
Classifier: Operating System :: POSIX :: Linux
Classifier: Programming Language :: Python :: 3
Requires-Python: >=3.9
